dotsanchez_cbxnz-2.5.0.dist-info/licenses/LICENSE
sanchez_cbxnz/__init__.py
sanchez_cbxnz/__main__.py
sanchez_cbxnz/channels.py
sanchez_cbxnz/decoder.py
sanchez_cbxnz/encoder.py
sanchez_cbxnz/format.py
sanchez_cbxnz/live.py
sanchez_cbxnz/player.py
sanchez_cbxnz/playlist.py
sanchez_cbxnz/py.typed
sanchez_cbxnz/streaming.py
sanchez_cbxnz/watermark.py
dotsanchez_cbxnz-2.5.0.dist-info/METADATA
dotsanchez_cbxnz-2.5.0.dist-info/WHEEL
dotsanchez_cbxnz-2.5.0.dist-info/entry_points.txt
dotsanchez_cbxnz-2.5.0.dist-info/top_level.txt
dotsanchez_cbxnz-2.5.0.dist-info/RECORD
