Metadata-Version: 2.4
Name: dotsanchez_cbxnz
Version: 2.5.0
Summary: Interdimensional Cable Video Format - A custom video format inspired by Rick & Morty
Author-email: cbx <cbgames.xyz@gmail.com>
License-Expression: MIT
Project-URL: Homepage, https://github.com/cbx-nz/dotsanchez-videostream
Project-URL: Repository, https://github.com/cbx-nz/dotsanchez-videostream
Project-URL: Issues, https://github.com/cbx-nz/dotsanchez-videostream/issues
Keywords: video,format,streaming,codec,rick-and-morty
Classifier: Development Status :: 4 - Beta
Classifier: Intended Audience :: Developers
Classifier: Operating System :: OS Independent
Classifier: Programming Language :: Python :: 3
Classifier: Programming Language :: Python :: 3.8
Classifier: Programming Language :: Python :: 3.9
Classifier: Programming Language :: Python :: 3.10
Classifier: Programming Language :: Python :: 3.11
Classifier: Programming Language :: Python :: 3.12
Classifier: Programming Language :: Python :: 3.13
Classifier: Programming Language :: Python :: 3.14
Classifier: Topic :: Multimedia :: Video
Classifier: Topic :: Multimedia :: Video :: Conversion
Requires-Python: >=3.8
License-File: LICENSE
Requires-Dist: numpy>=1.21.0
Requires-Dist: opencv-python>=4.5.0
Requires-Dist: Pillow>=8.0.0
Provides-Extra: player
Requires-Dist: pygame>=2.1.0; extra == "player"
Provides-Extra: live
Requires-Dist: mss>=6.0.0; extra == "live"
Provides-Extra: all
Requires-Dist: pygame>=2.1.0; extra == "all"
Requires-Dist: mss>=6.0.0; extra == "all"
Provides-Extra: dev
Requires-Dist: pytest>=7.0.0; extra == "dev"
Requires-Dist: pytest-cov>=4.0.0; extra == "dev"
Requires-Dist: black>=23.0.0; extra == "dev"
Requires-Dist: isort>=5.12.0; extra == "dev"
Dynamic: license-file
